fastapi_template_generator/__init__.py
fastapi_template_generator/__main__.py
fastapi_template_generator/generator.py
fastapi_template_generator/rules/api_design.md
fastapi_template_generator/rules/architecture.md
fastapi_template_generator/rules/database.md
fastapi_template_generator/rules/naming.md
fastapi_template_generator/templates/__init__.py
fastapi_template_generator/templates/app.py
fastapi_template_generator/templates/configs.py
fastapi_template_generator/templates/core.py
fastapi_template_generator/templates/middleware.py
fastapi_template_generator/templates/modules.py
fastapi_template_generator/templates/shared.py
fastapi_template_generator-0.0.1.dist-info/METADATA
fastapi_template_generator-0.0.1.dist-info/WHEEL
fastapi_template_generator-0.0.1.dist-info/entry_points.txt
fastapi_template_generator-0.0.1.dist-info/top_level.txt
fastapi_template_generator-0.0.1.dist-info/RECORD
