Metadata-Version: 2.4
Name: fastapi-template-generator
Version: 0.0.1
Summary: FastAPI project structure generator with best practices
Author-email: "Danil Boldyrev (daswer123)" <daswerq123@gmail.com>
Project-URL: Homepage, https://github.com/daswer123/fastapi-template-generator
Project-URL: Repository, https://github.com/daswer123/fastapi-template-generator
Classifier: Development Status :: 3 - Alpha
Classifier: Intended Audience :: Developers
Classifier: Topic :: Software Development :: Code Generators
Classifier: License :: OSI Approved :: MIT License
Classifier: Programming Language :: Python :: 3
Classifier: Programming Language :: Python :: 3.8
Classifier: Programming Language :: Python :: 3.9
Classifier: Programming Language :: Python :: 3.10
Classifier: Programming Language :: Python :: 3.11
Requires-Python: >=3.8
Requires-Dist: colorama>=0.4.6
